nerdbridge/__init__.py
nerdbridge/run.py
nerdbridge/scorecalc.py
nerdbridge/server.py
nerdbridge/textclient.py
nerdbridge-0.2.0.dist-info/entry_points.txt
nerdbridge-0.2.0.dist-info/LICENSE
nerdbridge-0.2.0.dist-info/METADATA
nerdbridge-0.2.0.dist-info/WHEEL
nerdbridge-0.2.0.dist-info/RECORD
