Metadata-Version: 2.1
Name: nerdbridge
Version: 0.2.0
Summary: server and client for playing bridge in asci format
License: GPL v3
Author: Pythor and Keumes
Requires-Python: >=3.8,<4.0
Classifier: License :: Other/Proprietary License
Classifier: Programming Language :: Python :: 3
Classifier: Programming Language :: Python :: 3.8
Classifier: Programming Language :: Python :: 3.9
Classifier: Programming Language :: Python :: 3.10
Classifier: Programming Language :: Python :: 3.11
